{
  "swagger": "2.0",
  "info": {
    "title": "user API",
    "description": "userAPI",
    "version": "1.0.0"
  },
  "host": "https://mainproject341-5ixv.onrender.com",
  "basePath": "/",
  "schemes": [
    "https"
  ],
  "paths": {
    "/login": {
      "get": {
        "description": "",
        "responses": {
          "default": {
            "description": ""
          }
        }
      }
    },
    "/logout": {
      "get": {
        "description": "",
        "responses": {
          "default": {
            "description": ""
          }
        }
      }
    },
    "/buyer/": {
      "get": {
        "tags": [
          "Buyers"
        ],
        "description": "",
        "produces": [
          "application/json"
        ],
        "responses": {
          "200": {
            "description": "OK"
          },
          "500": {
            "description": "Internal Server Error"
          }
        }
      },
      "post": {
        "tags": [
          "Buyers"
        ],
        "description": "",
        "parameters": [
          {
            "name": "body",
            "in": "body",
            "schema": {
              "type": "object",
              "properties": {
                "firstName": {
                  "example": "any"
                },
                "lastName": {
                  "example": "any"
                },
                "userName": {
                  "example": "any"
                }
              }
            }
          }
        ],
        "responses": {
          "200": {
            "description": "OK"
          },
          "400": {
            "description": "Bad Request"
          },
          "401": {
            "description": "Unauthorized"
          },
          "500": {
            "description": "Internal Server Error"
          }
        }
      }
    },
    "/buyer/{id}": {
      "get": {
        "tags": [
          "Buyers"
        ],
        "description": "",
        "produces": [
          "application/json"
        ],
        "parameters": [
          {
            "name": "id",
            "in": "path",
            "required": true,
            "type": "string"
          }
        ],
        "responses": {
          "200": {
            "description": "OK"
          },
          "500": {
            "description": "Internal Server Error"
          }
        }
      },
      "put": {
        "tags": [
          "Buyers"
        ],
        "description": "",
        "parameters": [
          {
            "name": "id",
            "in": "path",
            "required": true,
            "type": "string"
          },
          {
            "name": "body",
            "in": "body",
            "schema": {
              "type": "object",
              "properties": {
                "firstName": {
                  "example": "any"
                },
                "lastName": {
                  "example": "any"
                },
                "userName": {
                  "example": "any"
                }
              }
            }
          }
        ],
        "responses": {
          "200": {
            "description": "OK"
          },
          "400": {
            "description": "Bad Request"
          },
          "401": {
            "description": "Unauthorized"
          },
          "500": {
            "description": "Internal Server Error"
          }
        }
      },
      "delete": {
        "tags": [
          "Buyers"
        ],
        "description": "",
        "parameters": [
          {
            "name": "id",
            "in": "path",
            "required": true,
            "type": "string"
          }
        ],
        "responses": {
          "200": {
            "description": "OK"
          },
          "401": {
            "description": "Unauthorized"
          },
          "500": {
            "description": "Internal Server Error"
          }
        }
      }
    },
    "/seller/": {
      "get": {
        "tags": [
          "Sellers"
        ],
        "description": "",
        "produces": [
          "application/json"
        ],
        "responses": {
          "200": {
            "description": "OK"
          },
          "500": {
            "description": "Internal Server Error"
          }
        }
      },
      "post": {
        "tags": [
          "Sellers"
        ],
        "description": "",
        "parameters": [
          {
            "name": "body",
            "in": "body",
            "schema": {
              "type": "object",
              "properties": {
                "firstName": {
                  "example": "any"
                },
                "lastName": {
                  "example": "any"
                },
                "userName": {
                  "example": "any"
                }
              }
            }
          }
        ],
        "responses": {
          "200": {
            "description": "OK"
          },
          "400": {
            "description": "Bad Request"
          },
          "401": {
            "description": "Unauthorized"
          },
          "500": {
            "description": "Internal Server Error"
          }
        }
      }
    },
    "/seller/{id}": {
      "get": {
        "tags": [
          "Sellers"
        ],
        "description": "",
        "produces": [
          "application/json"
        ],
        "parameters": [
          {
            "name": "id",
            "in": "path",
            "required": true,
            "type": "string"
          }
        ],
        "responses": {
          "200": {
            "description": "OK"
          },
          "500": {
            "description": "Internal Server Error"
          }
        }
      },
      "put": {
        "tags": [
          "Sellers"
        ],
        "description": "",
        "parameters": [
          {
            "name": "id",
            "in": "path",
            "required": true,
            "type": "string"
          },
          {
            "name": "body",
            "in": "body",
            "schema": {
              "type": "object",
              "properties": {
                "firstName": {
                  "example": "any"
                },
                "lastName": {
                  "example": "any"
                },
                "userName": {
                  "example": "any"
                }
              }
            }
          }
        ],
        "responses": {
          "200": {
            "description": "OK"
          },
          "400": {
            "description": "Bad Request"
          },
          "401": {
            "description": "Unauthorized"
          },
          "500": {
            "description": "Internal Server Error"
          }
        }
      },
      "delete": {
        "tags": [
          "Sellers"
        ],
        "description": "",
        "parameters": [
          {
            "name": "id",
            "in": "path",
            "required": true,
            "type": "string"
          }
        ],
        "responses": {
          "200": {
            "description": "OK"
          },
          "401": {
            "description": "Unauthorized"
          },
          "500": {
            "description": "Internal Server Error"
          }
        }
      }
    },
    "/product/{sellerId}": {
      "get": {
        "tags": [
          "Products"
        ],
        "description": "",
        "produces": [
          "application/json"
        ],
        "parameters": [
          {
            "name": "sellerId",
            "in": "path",
            "required": true,
            "type": "string"
          }
        ],
        "responses": {
          "200": {
            "description": "OK"
          },
          "500": {
            "description": "Internal Server Error"
          }
        }
      },
      "post": {
        "tags": [
          "Products"
        ],
        "description": "",
        "parameters": [
          {
            "name": "sellerId",
            "in": "path",
            "required": true,
            "type": "string"
          },
          {
            "name": "body",
            "in": "body",
            "schema": {
              "type": "object",
              "properties": {
                "productName": {
                  "example": "any"
                },
                "description": {
                  "example": "any"
                },
                "price": {
                  "example": "any"
                },
                "location": {
                  "example": "any"
                },
                "warranty": {
                  "example": "any"
                },
                "stock": {
                  "example": "any"
                }
              }
            }
          }
        ],
        "responses": {
          "200": {
            "description": "OK"
          },
          "400": {
            "description": "Bad Request"
          },
          "401": {
            "description": "Unauthorized"
          },
          "500": {
            "description": "Internal Server Error"
          }
        }
      }
    },
    "/product/{sellerId}/{productId}": {
      "get": {
        "tags": [
          "Products"
        ],
        "description": "",
        "produces": [
          "application/json"
        ],
        "parameters": [
          {
            "name": "sellerId",
            "in": "path",
            "required": true,
            "type": "string"
          },
          {
            "name": "productId",
            "in": "path",
            "required": true,
            "type": "string"
          }
        ],
        "responses": {
          "200": {
            "description": "OK"
          },
          "500": {
            "description": "Internal Server Error"
          }
        }
      },
      "put": {
        "tags": [
          "Products"
        ],
        "description": "",
        "parameters": [
          {
            "name": "sellerId",
            "in": "path",
            "required": true,
            "type": "string"
          },
          {
            "name": "productId",
            "in": "path",
            "required": true,
            "type": "string"
          },
          {
            "name": "body",
            "in": "body",
            "schema": {
              "type": "object",
              "properties": {
                "productName": {
                  "example": "any"
                },
                "description": {
                  "example": "any"
                },
                "price": {
                  "example": "any"
                },
                "location": {
                  "example": "any"
                },
                "warranty": {
                  "example": "any"
                },
                "stock": {
                  "example": "any"
                }
              }
            }
          }
        ],
        "responses": {
          "200": {
            "description": "OK"
          },
          "400": {
            "description": "Bad Request"
          },
          "401": {
            "description": "Unauthorized"
          },
          "500": {
            "description": "Internal Server Error"
          }
        }
      },
      "delete": {
        "tags": [
          "Products"
        ],
        "description": "",
        "parameters": [
          {
            "name": "sellerId",
            "in": "path",
            "required": true,
            "type": "string"
          },
          {
            "name": "productId",
            "in": "path",
            "required": true,
            "type": "string"
          }
        ],
        "responses": {
          "200": {
            "description": "OK"
          },
          "401": {
            "description": "Unauthorized"
          },
          "500": {
            "description": "Internal Server Error"
          }
        }
      }
    },
    "/order/{buyerId}": {
      "get": {
        "tags": [
          "Orders"
        ],
        "description": "",
        "produces": [
          "application/json"
        ],
        "parameters": [
          {
            "name": "buyerId",
            "in": "path",
            "required": true,
            "type": "string"
          }
        ],
        "responses": {
          "200": {
            "description": "OK"
          },
          "500": {
            "description": "Internal Server Error"
          }
        }
      }
    },
    "/order/{buyerId}/{orderId}": {
      "get": {
        "tags": [
          "Orders"
        ],
        "description": "",
        "produces": [
          "application/json"
        ],
        "parameters": [
          {
            "name": "buyerId",
            "in": "path",
            "required": true,
            "type": "string"
          },
          {
            "name": "orderId",
            "in": "path",
            "required": true,
            "type": "string"
          }
        ],
        "responses": {
          "200": {
            "description": "OK"
          },
          "404": {
            "description": "Not Found"
          },
          "500": {
            "description": "Internal Server Error"
          }
        }
      },
      "put": {
        "tags": [
          "Orders"
        ],
        "description": "",
        "parameters": [
          {
            "name": "buyerId",
            "in": "path",
            "required": true,
            "type": "string"
          },
          {
            "name": "orderId",
            "in": "path",
            "required": true,
            "type": "string"
          },
          {
            "name": "body",
            "in": "body",
            "schema": {
              "type": "object",
              "properties": {
                "quantity": {
                  "example": "any"
                }
              }
            }
          }
        ],
        "responses": {
          "200": {
            "description": "OK"
          },
          "400": {
            "description": "Bad Request"
          },
          "401": {
            "description": "Unauthorized"
          },
          "404": {
            "description": "Not Found"
          },
          "500": {
            "description": "Internal Server Error"
          }
        }
      },
      "delete": {
        "tags": [
          "Orders"
        ],
        "description": "",
        "parameters": [
          {
            "name": "buyerId",
            "in": "path",
            "required": true,
            "type": "string"
          },
          {
            "name": "orderId",
            "in": "path",
            "required": true,
            "type": "string"
          }
        ],
        "responses": {
          "200": {
            "description": "OK"
          },
          "401": {
            "description": "Unauthorized"
          },
          "404": {
            "description": "Not Found"
          },
          "500": {
            "description": "Internal Server Error"
          }
        }
      }
    },
    "/order/{buyerid}/{sellerid}/{productid}": {
      "post": {
        "tags": [
          "Orders"
        ],
        "description": "",
        "parameters": [
          {
            "name": "buyerid",
            "in": "path",
            "required": true,
            "type": "string"
          },
          {
            "name": "sellerid",
            "in": "path",
            "required": true,
            "type": "string"
          },
          {
            "name": "productid",
            "in": "path",
            "required": true,
            "type": "string"
          },
          {
            "name": "body",
            "in": "body",
            "schema": {
              "type": "object",
              "properties": {
                "quantity": {
                  "example": "any"
                }
              }
            }
          }
        ],
        "responses": {
          "201": {
            "description": "Created"
          },
          "400": {
            "description": "Bad Request"
          },
          "401": {
            "description": "Unauthorized"
          },
          "404": {
            "description": "Not Found"
          },
          "500": {
            "description": "Internal Server Error"
          }
        }
      }
    },
    "/payment/{buyerId}": {
      "get": {
        "tags": [
          "Payments"
        ],
        "description": "",
        "produces": [
          "application/json"
        ],
        "parameters": [
          {
            "name": "buyerId",
            "in": "path",
            "required": true,
            "type": "string"
          }
        ],
        "responses": {
          "200": {
            "description": "OK"
          },
          "500": {
            "description": "Internal Server Error"
          }
        }
      }
    },
    "/payment/{orderId}": {
      "post": {
        "tags": [
          "Payments"
        ],
        "description": "",
        "parameters": [
          {
            "name": "orderId",
            "in": "path",
            "required": true,
            "type": "string"
          },
          {
            "name": "body",
            "in": "body",
            "schema": {
              "type": "object",
              "properties": {
                "cardInfo": {
                  "example": "any"
                }
              }
            }
          }
        ],
        "responses": {
          "201": {
            "description": "Created"
          },
          "400": {
            "description": "Bad Request"
          },
          "401": {
            "description": "Unauthorized"
          },
          "404": {
            "description": "Not Found"
          },
          "500": {
            "description": "Internal Server Error"
          }
        }
      }
    },
    "/payment/{buyerId}/{id}": {
      "get": {
        "tags": [
          "Payments"
        ],
        "description": "",
        "produces": [
          "application/json"
        ],
        "parameters": [
          {
            "name": "buyerId",
            "in": "path",
            "required": true,
            "type": "string"
          },
          {
            "name": "id",
            "in": "path",
            "required": true,
            "type": "string"
          }
        ],
        "responses": {
          "200": {
            "description": "OK"
          },
          "500": {
            "description": "Internal Server Error"
          }
        }
      },
      "put": {
        "tags": [
          "Payments"
        ],
        "description": "",
        "parameters": [
          {
            "name": "buyerId",
            "in": "path",
            "required": true,
            "type": "string"
          },
          {
            "name": "id",
            "in": "path",
            "required": true,
            "type": "string"
          },
          {
            "name": "body",
            "in": "body",
            "schema": {
              "type": "object",
              "properties": {
                "cardInfo": {
                  "example": "any"
                }
              }
            }
          }
        ],
        "responses": {
          "200": {
            "description": "OK"
          },
          "400": {
            "description": "Bad Request"
          },
          "401": {
            "description": "Unauthorized"
          },
          "500": {
            "description": "Internal Server Error"
          }
        }
      },
      "delete": {
        "tags": [
          "Payments"
        ],
        "description": "",
        "parameters": [
          {
            "name": "buyerId",
            "in": "path",
            "required": true,
            "type": "string"
          },
          {
            "name": "id",
            "in": "path",
            "required": true,
            "type": "string"
          }
        ],
        "responses": {
          "200": {
            "description": "OK"
          },
          "401": {
            "description": "Unauthorized"
          },
          "404": {
            "description": "Not Found"
          },
          "500": {
            "description": "Internal Server Error"
          }
        }
      }
    }
  }
}